stashpy/__init__.py
stashpy/constants.py
stashpy/handler.py
stashpy/indexer.py
stashpy/main.py
stashpy/pattern_matching.py
stashpy/processor.py
stashpy/patterns/grok_patterns.txt
stashpy-0.2.1.dist-info/DESCRIPTION.rst
stashpy-0.2.1.dist-info/METADATA
stashpy-0.2.1.dist-info/RECORD
stashpy-0.2.1.dist-info/WHEEL
stashpy-0.2.1.dist-info/entry_points.txt
stashpy-0.2.1.dist-info/metadata.json
stashpy-0.2.1.dist-info/top_level.txt
